cargo_parse/__init__.py
cargo_parse/models/__init__.py
cargo_parse/models/badges.py
cargo_parse/models/cargo_toml.py
cargo_parse/models/core.py
cargo_parse/models/dependency.py
cargo_parse/models/features.py
cargo_parse/models/lib.py
cargo_parse/models/manifest.py
cargo_parse/models/package.py
cargo_parse/models/patch.py
cargo_parse/models/profile.py
cargo_parse/models/workspace.py
cargo_parse/parse.py
cargo_parse/util.py
cargo_parse-0.1.0.dist-info/LICENSE
cargo_parse-0.1.0.dist-info/WHEEL
cargo_parse-0.1.0.dist-info/METADATA
cargo_parse-0.1.0.dist-info/RECORD
