Metadata-Version: 2.1
Name: cargo-parse
Version: 0.1.0
Summary: Library to parse the Cargo.toml manifest file.
Home-page: https://github.com/Deca-Technologies/cargo-parse
License: MIT
Keywords: cargo,rust
Author: Andrew Hoetker
Author-email: andrew.hoetker@thinkdeca.com
Requires-Python: >=3.7,<4.0
Classifier: License :: OSI Approved :: MIT License
Classifier: Programming Language :: Python :: 3
Classifier: Programming Language :: Python :: 3.10
Classifier: Programming Language :: Python :: 3.7
Classifier: Programming Language :: Python :: 3.8
Classifier: Programming Language :: Python :: 3.9
Requires-Dist: pydantic (>=1.8.2,<2.0.0)
Requires-Dist: toml (>=0.10.2,<0.11.0)
Project-URL: Repository, https://github.com/Deca-Technologies/cargo-parse
